{"lots": [{"coordinates": [[1813, 2870], [1813, 1742], [789, 1742], [789, 2870]], "label": 1}, {"coordinates": [[1392, 3000], [1392, 2058], [477, 2058], [477, 3000]], "label": 0}, {"coordinates": [[2998, 3000], [2998, 1997], [1810, 1997], [1810, 3000]], "label": 0}, {"coordinates": [[2186, 2430], [2186, 1418], [1128, 1418], [1128, 2430]], "label": 1}, {"coordinates": [[3222, 2600], [3222, 1603], [2195, 1603], [2195, 2600]], "label": 1}, {"coordinates": [[2491, 1988], [2491, 1124], [1483, 1124], [1483, 1988]], "label": 0}, {"coordinates": [[3376, 2164], [3376, 1291], [2497, 1291], [2497, 2164]], "label": 0}, {"coordinates": [[2726, 1604], [2726, 903], [1818, 903], [1818, 1604]], "label": 0}, {"coordinates": [[2880, 1292], [2880, 727], [2088, 727], [2088, 1292]], "label": 0}, {"coordinates": [[3470, 1771], [3470, 1064], [2729, 1064], [2729, 1771]], "label": 0}, {"coordinates": [[3529, 1473], [3529, 885], [2888, 885], [2888, 1473]], "label": 1}, {"coordinates": [[3011, 1065], [3011, 595], [2308, 595], [2308, 1065]], "label": 0}, {"coordinates": [[3093, 887], [3093, 496], [2485, 496], [2485, 887]], "label": 1}, {"coordinates": [[3161, 748], [3161, 423], [2620, 423], [2620, 748]], "label": 1}, {"coordinates": [[3594, 1060], [3594, 645], [3096, 645], [3096, 1060]], "label": 0}, {"coordinates": [[3566, 1241], [3566, 749], [3005, 749], [3005, 1241]], "label": 0}, {"coordinates": [[397, 1581], [397, 1073], [89, 1073], [89, 1581]], "label": 0}, {"coordinates": [[282, 1261], [282, 887], [52, 887], [52, 1261]], "label": 0}, {"coordinates": [[497, 1073], [497, 732], [221, 732], [221, 1073]], "label": 0}, {"coordinates": [[646, 1343], [646, 888], [281, 888], [281, 1343]], "label": 1}, {"coordinates": [[902, 1104], [902, 721], [497, 721], [497, 1104]], "label": 1}, {"coordinates": [[712, 887], [712, 596], [405, 596], [405, 887]], "label": 1}, {"coordinates": [[930, 723], [930, 465], [585, 465], [585, 723]], "label": 1}, {"coordinates": [[1164, 899], [1164, 567], [712, 567], [712, 899]], "label": 0}, {"coordinates": [[1143, 569], [1143, 361], [775, 361], [775, 569]], "label": 0}, {"coordinates": [[1405, 708], [1405, 438], [932, 438], [932, 708]], "label": 0}, {"coordinates": [[1627, 557], [1627, 334], [1141, 334], [1141, 557]], "label": 0}, {"coordinates": [[1343, 437], [1343, 267], [957, 267], [957, 437]], "label": 1}, {"coordinates": [[1519, 334], [1519, 184], [1134, 184], [1134, 334]], "label": 0}, {"coordinates": [[1822, 431], [1822, 247], [1346, 247], [1346, 431]], "label": 1}, {"coordinates": [[1991, 333], [1991, 173], [1522, 173], [1522, 333]], "label": 1}, {"coordinates": [[1684, 246], [1684, 117], [1302, 117], [1302, 246]], "label": 0}, {"coordinates": [[1837, 173], [1837, 66], [1460, 66], [1460, 173]], "label": 1}, {"coordinates": [[2122, 257], [2122, 118], [1683, 118], [1683, 257]], "label": 0}, {"coordinates": [[167, 802], [167, 626], [22, 626], [22, 802]], "label": 0}, {"coordinates": [[279, 623], [279, 467], [133, 467], [133, 623]], "label": 1}, {"coordinates": [[312, 701], [312, 523], [148, 523], [148, 701]], "label": 1}, {"coordinates": [[149, 723], [149, 557], [18, 557], [18, 723]], "label": 1}, {"coordinates": [[412, 520], [412, 387], [252, 387], [252, 520]], "label": 1}, {"coordinates": [[460, 582], [460, 431], [280, 431], [280, 582]], "label": 0}, {"coordinates": [[546, 429], [546, 302], [370, 302], [370, 429]], "label": 0}, {"coordinates": [[613, 477], [613, 339], [412, 339], [412, 477]], "label": 0}, {"coordinates": [[760, 375], [760, 257], [545, 257], [545, 375]], "label": 0}, {"coordinates": [[676, 337], [676, 228], [488, 228], [488, 337]], "label": 1}, {"coordinates": [[813, 256], [813, 167], [604, 167], [604, 256]], "label": 1}, {"coordinates": [[910, 290], [910, 185], [676, 185], [676, 290]], "label": 0}, {"coordinates": [[1058, 209], [1058, 117], [812, 117], [812, 209]], "label": 1}, {"coordinates": [[943, 185], [943, 103], [729, 103], [729, 185]], "label": 0}, {"coordinates": [[1186, 136], [1186, 63], [948, 63], [948, 136]], "label": 0}, {"coordinates": [[1060, 117], [1060, 55], [850, 55], [850, 117]], "label": 1}, {"coordinates": [[116, 550], [116, 443], [19, 443], [19, 550]], "label": 1}, {"coordinates": [[109, 508], [109, 410], [20, 410], [20, 508]], "label": 1}, {"coordinates": [[219, 477], [219, 373], [110, 373], [110, 477]], "label": 1}, {"coordinates": [[204, 441], [204, 350], [104, 350], [104, 441]], "label": 1}, {"coordinates": [[319, 406], [319, 312], [204, 312], [204, 406]], "label": 1}, {"coordinates": [[298, 374], [298, 291], [189, 291], [189, 374]], "label": 1}, {"coordinates": [[422, 334], [422, 248], [296, 248], [296, 334]], "label": 1}, {"coordinates": [[516, 267], [516, 191], [389, 191], [389, 267]], "label": 1}, {"coordinates": [[482, 248], [482, 179], [358, 179], [358, 248]], "label": 1}, {"coordinates": [[629, 205], [629, 135], [483, 135], [483, 205]], "label": 1}, {"coordinates": [[731, 145], [731, 85], [580, 85], [580, 145]], "label": 1}, {"coordinates": [[829, 90], [829, 41], [669, 41], [669, 90]], "label": 1}, {"coordinates": [[760, 83], [760, 39], [616, 39], [616, 83]], "label": 1}, {"coordinates": [[671, 131], [671, 79], [537, 79], [537, 131]], "label": 1}, {"coordinates": [[583, 187], [583, 123], [447, 123], [447, 187]], "label": 1}, {"coordinates": [[1183, 62], [1183, 3], [941, 3], [941, 62]], "label": 1}, {"coordinates": [[1313, 75], [1313, 13], [1063, 13], [1063, 75]], "label": 0}]}