{"lots": [{"coordinates": [[2394, 2655], [2394, 1653], [1312, 1653], [1312, 2655]], "label": 1}, {"coordinates": [[3223, 3000], [3223, 2202], [2057, 2202], [2057, 3000]], "label": 1}, {"coordinates": [[3382, 2737], [3382, 1821], [2394, 1821], [2394, 2737]], "label": 0}, {"coordinates": [[2657, 2205], [2657, 1378], [1664, 1378], [1664, 2205]], "label": 0}, {"coordinates": [[3493, 2277], [3493, 1520], [2657, 1520], [2657, 2277]], "label": 1}, {"coordinates": [[2830, 1814], [2830, 1164], [1968, 1164], [1968, 1814]], "label": 0}, {"coordinates": [[3527, 1896], [3527, 1291], [2828, 1291], [2828, 1896]], "label": 0}, {"coordinates": [[2962, 1515], [2962, 997], [2201, 997], [2201, 1515]], "label": 0}, {"coordinates": [[3553, 1640], [3553, 1126], [2965, 1126], [2965, 1640]], "label": 1}, {"coordinates": [[3046, 1293], [3046, 873], [2393, 873], [2393, 1293]], "label": 0}, {"coordinates": [[3566, 1416], [3566, 998], [3039, 998], [3039, 1416]], "label": 1}, {"coordinates": [[3101, 1126], [3101, 788], [2537, 788], [2537, 1126]], "label": 1}, {"coordinates": [[3571, 1253], [3571, 890], [3097, 890], [3097, 1253]], "label": 0}, {"coordinates": [[3569, 1116], [3569, 802], [3153, 802], [3153, 1116]], "label": 0}, {"coordinates": [[3150, 997], [3150, 710], [2637, 710], [2637, 997]], "label": 1}, {"coordinates": [[3189, 892], [3189, 633], [2725, 633], [2725, 892]], "label": 0}, {"coordinates": [[3218, 804], [3218, 582], [2810, 582], [2810, 804]], "label": 1}, {"coordinates": [[3566, 1008], [3566, 738], [3194, 738], [3194, 1008]], "label": 0}, {"coordinates": [[3565, 922], [3565, 683], [3219, 683], [3219, 922]], "label": 1}, {"coordinates": [[3241, 740], [3241, 538], [2865, 538], [2865, 740]], "label": 0}, {"coordinates": [[3259, 685], [3259, 501], [2918, 501], [2918, 685]], "label": 0}, {"coordinates": [[3564, 842], [3564, 635], [3243, 635], [3243, 842]], "label": 1}, {"coordinates": [[3278, 634], [3278, 468], [2965, 468], [2965, 634]], "label": 1}, {"coordinates": [[3557, 778], [3557, 583], [3258, 583], [3258, 778]], "label": 0}, {"coordinates": [[318, 1904], [318, 1375], [26, 1375], [26, 1904]], "label": 0}, {"coordinates": [[588, 1679], [588, 1205], [223, 1205], [223, 1679]], "label": 1}, {"coordinates": [[224, 1564], [224, 1157], [0, 1157], [0, 1564]], "label": 1}, {"coordinates": [[459, 1375], [459, 1036], [181, 1036], [181, 1375]], "label": 1}, {"coordinates": [[815, 1111], [815, 836], [488, 836], [488, 1111]], "label": 1}, {"coordinates": [[1017, 1322], [1017, 959], [591, 959], [591, 1322]], "label": 1}, {"coordinates": [[1274, 1131], [1274, 835], [815, 835], [815, 1131]], "label": 1}, {"coordinates": [[1024, 959], [1024, 739], [683, 739], [683, 959]], "label": 1}, {"coordinates": [[1504, 966], [1504, 716], [1024, 716], [1024, 966]], "label": 0}, {"coordinates": [[1240, 835], [1240, 635], [849, 635], [849, 835]], "label": 1}, {"coordinates": [[1424, 717], [1424, 554], [1052, 554], [1052, 717]], "label": 1}, {"coordinates": [[1704, 829], [1704, 619], [1239, 619], [1239, 829]], "label": 0}, {"coordinates": [[1882, 719], [1882, 547], [1421, 547], [1421, 719]], "label": 1}, {"coordinates": [[2038, 632], [2038, 486], [1591, 486], [1591, 632]], "label": 0}, {"coordinates": [[1587, 620], [1587, 481], [1227, 481], [1227, 620]], "label": 1}, {"coordinates": [[1742, 546], [1742, 431], [1380, 431], [1380, 546]], "label": 1}, {"coordinates": [[2164, 560], [2164, 432], [1746, 432], [1746, 560]], "label": 0}, {"coordinates": [[1884, 485], [1884, 376], [1503, 376], [1503, 485]], "label": 0}, {"coordinates": [[2002, 431], [2002, 337], [1655, 337], [1655, 431]], "label": 1}, {"coordinates": [[2278, 503], [2278, 388], [1886, 388], [1886, 503]], "label": 0}, {"coordinates": [[2375, 459], [2375, 356], [2000, 356], [2000, 459]], "label": 0}, {"coordinates": [[2457, 418], [2457, 324], [2109, 324], [2109, 418]], "label": 1}, {"coordinates": [[2526, 388], [2526, 299], [2207, 299], [2207, 388]], "label": 0}, {"coordinates": [[2590, 361], [2590, 280], [2287, 280], [2287, 361]], "label": 0}, {"coordinates": [[2105, 387], [2105, 302], [1778, 302], [1778, 387]], "label": 1}, {"coordinates": [[2207, 357], [2207, 278], [1885, 278], [1885, 357]], "label": 0}, {"coordinates": [[2285, 322], [2285, 256], [1989, 256], [1989, 322]], "label": 1}, {"coordinates": [[2362, 299], [2362, 236], [2069, 236], [2069, 299]], "label": 1}, {"coordinates": [[2423, 279], [2423, 221], [2160, 221], [2160, 279]], "label": 1}, {"coordinates": [[1814, 3000], [1814, 2198], [726, 2198], [726, 3000]], "label": 1}, {"coordinates": [[1042, 3000], [1042, 2553], [405, 2553], [405, 3000]], "label": 0}, {"coordinates": [[150, 1086], [150, 885], [7, 885], [7, 1086]], "label": 1}, {"coordinates": [[305, 975], [305, 795], [139, 795], [139, 975]], "label": 1}, {"coordinates": [[548, 807], [548, 666], [355, 666], [355, 807]], "label": 1}, {"coordinates": [[699, 716], [699, 590], [489, 590], [489, 716]], "label": 1}, {"coordinates": [[846, 629], [846, 524], [626, 524], [626, 629]], "label": 1}, {"coordinates": [[989, 553], [989, 459], [751, 459], [751, 553]], "label": 0}, {"coordinates": [[1123, 487], [1123, 409], [882, 409], [882, 487]], "label": 1}, {"coordinates": [[1247, 428], [1247, 361], [1003, 361], [1003, 428]], "label": 1}, {"coordinates": [[1371, 377], [1371, 317], [1126, 317], [1126, 377]], "label": 1}, {"coordinates": [[1487, 333], [1487, 283], [1226, 283], [1226, 333]], "label": 1}, {"coordinates": [[627, 666], [627, 554], [444, 554], [444, 666]], "label": 1}, {"coordinates": [[753, 589], [753, 500], [563, 500], [563, 589]], "label": 1}, {"coordinates": [[882, 523], [882, 436], [674, 436], [674, 523]], "label": 1}, {"coordinates": [[1006, 458], [1006, 387], [802, 387], [802, 458]], "label": 1}, {"coordinates": [[1122, 407], [1122, 343], [910, 343], [910, 407]], "label": 1}, {"coordinates": [[140, 972], [140, 819], [15, 819], [15, 972]], "label": 1}, {"coordinates": [[274, 888], [274, 738], [130, 738], [130, 888]], "label": 1}]}